CHANGELOG.md
kosmorro/__init__.py
kosmorro/__main__.py
kosmorro/assets/moonphases/png/first-quarter.png
kosmorro/assets/moonphases/png/full-moon.png
kosmorro/assets/moonphases/png/last-quarter.png
kosmorro/assets/moonphases/png/new-moon.png
kosmorro/assets/moonphases/png/unknown.png
kosmorro/assets/moonphases/png/waning-crescent.png
kosmorro/assets/moonphases/png/waning-gibbous.png
kosmorro/assets/moonphases/png/waxing-crescent.png
kosmorro/assets/moonphases/png/waxing-gibbous.png
kosmorro/assets/moonphases/svg/first-quarter.svg
kosmorro/assets/moonphases/svg/full-moon.svg
kosmorro/assets/moonphases/svg/last-quarter.svg
kosmorro/assets/moonphases/svg/new-moon.svg
kosmorro/assets/moonphases/svg/unknown.svg
kosmorro/assets/moonphases/svg/waning-crescent.svg
kosmorro/assets/moonphases/svg/waning-gibbous.svg
kosmorro/assets/moonphases/svg/waxing-crescent.svg
kosmorro/assets/moonphases/svg/waxing-gibbous.svg
kosmorro/assets/pdf/kosmorro.sty
kosmorro/assets/pdf/template.tex
kosmorro/assets/png/kosmorro-icon-white.png
kosmorro/assets/png/kosmorro-icon.png
kosmorro/assets/png/kosmorro-logo-white.png
kosmorro/assets/png/kosmorro-logo.png
kosmorro/assets/svg/kosmorro-icon-white.svg
kosmorro/assets/svg/kosmorro-icon.svg
kosmorro/assets/svg/kosmorro-logo-white.svg
kosmorro/assets/svg/kosmorro-logo.svg
kosmorro/date.py
kosmorro/debug.py
kosmorro/dumper.py
kosmorro/environment.py
kosmorro/exceptions.py
kosmorro/i18n/__init__.py
kosmorro/i18n/strings.py
kosmorro/i18n/utils.py
kosmorro/locales/de/LC_MESSAGES/messages.mo
kosmorro/locales/de/LC_MESSAGES/messages.po
kosmorro/locales/es/LC_MESSAGES/messages.mo
kosmorro/locales/es/LC_MESSAGES/messages.po
kosmorro/locales/fr/LC_MESSAGES/messages.mo
kosmorro/locales/fr/LC_MESSAGES/messages.po
kosmorro/locales/messages.pot
kosmorro/locales/nb_NO/LC_MESSAGES/messages.mo
kosmorro/locales/nb_NO/LC_MESSAGES/messages.po
kosmorro/locales/nl/LC_MESSAGES/messages.mo
kosmorro/locales/nl/LC_MESSAGES/messages.po
kosmorro-0.10.13.dist-info/LICENSE.md
kosmorro-0.10.13.dist-info/METADATA
kosmorro-0.10.13.dist-info/WHEEL
kosmorro-0.10.13.dist-info/entry_points.txt
kosmorro-0.10.13.dist-info/RECORD
