Metadata-Version: 2.1
Name: kosmorro
Version: 0.10.13
Summary: A program to compute the ephemerides.
License: AGPL-3.0-or-later
Author: Jérôme Deuchnord
Author-email: jerome@deuchnord.fr
Requires-Python: >=3.8,<4.0
Classifier: License :: OSI Approved :: GNU Affero General Public License v3 or later (AGPLv3+)
Classifier: Programming Language :: Python :: 3
Classifier: Programming Language :: Python :: 3.8
Classifier: Programming Language :: Python :: 3.9
Classifier: Programming Language :: Python :: 3.10
Classifier: Programming Language :: Python :: 3.11
Classifier: Programming Language :: Python :: 3.12
Requires-Dist: Babel (>=2.9,<3.0)
Requires-Dist: importlib-metadata (>=4.11,<8.0)
Requires-Dist: kosmorrolib (>=1.0,<2.0)
Requires-Dist: python-dateutil (>=2.8,<3.0)
Requires-Dist: tabulate (>=0.8,<0.10)
Requires-Dist: termcolor (>=1.1,<3.0)
